lxfx/project_config.py
lxfx/gui/GraphingView.py
lxfx/gui/__init__.py
lxfx/gui/axes.py
lxfx/gui/candleBody.py
lxfx/gui/candleStickDataStream.py
lxfx/gui/candleStickState.py
lxfx/gui/candleStickWick.py
lxfx/gui/charting.py
lxfx/gui/data.py
lxfx/gui/dataCollection.py
lxfx/gui/dbManager.py
lxfx/gui/figures.py
lxfx/gui/graph.py
lxfx/gui/graphTimeFrameNode.py
lxfx/gui/graphWindow.py
lxfx/gui/indicators.py
lxfx/gui/leftClickWidget.py
lxfx/gui/lxfxView.py
lxfx/gui/mainwindow.py
lxfx/gui/modelsWidget.py
lxfx/gui/pathGraphPoint.py
lxfx/gui/strategies.py
lxfx/gui/tViewLine.py
lxfx/gui/tickerInstance.py
lxfx/gui/utils.py
lxfx/models/__init__.py
lxfx/models/config.py
lxfx/models/data.py
lxfx/models/experiments.py
lxfx/models/metrics.py
lxfx/models/models.py
lxfx/models/predPlotter.py
lxfx/models/trainers.py
lxfx/models/utils.py
lxfx/models/xfx.py
lxfx-0.0.13.dist-info/LICENSE
lxfx-0.0.13.dist-info/METADATA
lxfx-0.0.13.dist-info/WHEEL
lxfx-0.0.13.dist-info/top_level.txt
lxfx-0.0.13.dist-info/RECORD
