Metadata-Version: 2.1
Name: lxfx
Version: 0.0.13
Summary: lxfx is a comprehensive library designed for time series analysis and experimentation. 
Author-email: MATOVU EZRA TIMOTHY <ezratimothy600@gmail.com>
License:                                  Apache License
Project-URL: Home, https://github.com/timothy-voiuhy/lxfx
Project-URL: Documentation, https://github.com/timothy-voiuhy/lxfx/wiki
Project-URL: Issues, https://github.com/timothy-voiuhy/lxfx/issues
Classifier: License :: OSI Approved :: Apache Software License
Classifier: Programming Language :: Python :: 3
Classifier: Programming Language :: Python :: 3.8
Classifier: Programming Language :: Python :: 3.9
Classifier: Programming Language :: Python :: 3.10
Classifier: Programming Language :: Python :: 3.11
Classifier: Intended Audience :: Developers
Classifier: Intended Audience :: Science/Research
Classifier: Topic :: Software Development :: Libraries :: Python Modules
Classifier: Topic :: Scientific/Engineering :: Artificial Intelligence
Requires-Python: >=3.8
License-File: LICENSE
Requires-Dist: torch>=1.7.0
Requires-Dist: numpy>=1.19.0
Requires-Dist: pandas>=1.1.0
Requires-Dist: matplotlib>=3.3.0
Requires-Dist: plotly>=4.9.0
Requires-Dist: tqdm>=4.50.0
Requires-Dist: scikit-learn>=0.23.0
Requires-Dist: statsmodels>=0.12.0
Requires-Dist: icecream
Requires-Dist: ta
